gmsh_interop/__init__.py
gmsh_interop/node_tuples.py
gmsh_interop/reader.py
gmsh_interop/runner.py
gmsh_interop/version.py
gmsh_interop-2024.1.dist-info/LICENSE
gmsh_interop-2024.1.dist-info/METADATA
gmsh_interop-2024.1.dist-info/WHEEL
gmsh_interop-2024.1.dist-info/top_level.txt
gmsh_interop-2024.1.dist-info/RECORD
