Metadata-Version: 2.1
Name: gmsh_interop
Version: 2024.1
Summary: A parser for GMSH's .msh format
Home-page: http://github.com/inducer/gmsh_interop
Author: Andreas Kloeckner
Author-email: inform@tiker.net
License: MIT
Classifier: Development Status :: 4 - Beta
Classifier: Intended Audience :: Developers
Classifier: Intended Audience :: Other Audience
Classifier: Intended Audience :: Science/Research
Classifier: License :: OSI Approved :: MIT License
Classifier: Natural Language :: English
Classifier: Programming Language :: Python
Classifier: Programming Language :: Python
Classifier: Programming Language :: Python :: 3
Classifier: Programming Language :: Python :: 3.3
Classifier: Programming Language :: Python :: 3.4
Classifier: Topic :: Scientific/Engineering
Classifier: Topic :: Scientific/Engineering :: Information Analysis
Classifier: Topic :: Scientific/Engineering :: Mathematics
Classifier: Topic :: Scientific/Engineering :: Visualization
Classifier: Topic :: Software Development :: Libraries
Classifier: Topic :: Utilities
Requires-Python: ~=3.8
License-File: LICENSE
Requires-Dist: numpy>=1.6.0
Requires-Dist: pytools
Requires-Dist: packaging>=20.0
